LICENSE.rst
MANIFEST.in
README.rst
setup.cfg
setup.py
Mezcal/Barrel.py
Mezcal/README.md
Mezcal/__init__.py
Mezcal/mezcal.bz2.png
Mezcal.egg-info/PKG-INFO
Mezcal.egg-info/SOURCES.txt
Mezcal.egg-info/dependency_links.txt
Mezcal.egg-info/requires.txt
Mezcal.egg-info/top_level.txt
Mezcal/widget/Bottle.py
Mezcal/widget/SampleWidget.py
Mezcal/widget/Ui_MezcalPicker.py
Mezcal/widget/g.gif
Mezcal/widget/widget.ui