Metadata-Version: 1.1
Name: Mezcal
Version: 1.0.4
Summary: Library for generating a set of color schemes from a provided color.
Home-page: https://github.com/pakalolo-papalote/Mezcal
Author: Pakalolo Papalote
Author-email: pakalolo.papalote@neurok.org
License: CC0 1.0
Keywords: color colour scheme complimentary analogous split-complimentary triads tetrads monochromatic theme selection
Platform: UNKNOWN
Classifier: Development Status :: 5 - Production/Stable
Classifier: Intended Audience :: Developers
Classifier: Intended Audience :: End Users/Desktop
Classifier: Topic :: Artistic Software
Classifier: Topic :: Multimedia
Classifier: Topic :: Multimedia :: Graphics
Classifier: Topic :: Utilities
Classifier: License :: CC0 1.0 Universal (CC0 1.0) Public Domain Dedication
Classifier: Programming Language :: Python :: 3.4
Classifier: Programming Language :: Python :: 3.5
